pyapiconsoleir/__init__.py
pyapiconsoleir/client.py
pyapiconsoleir/const.py
pyapiconsoleir/exceptions.py
pyapiconsoleir/responses.py
pyapiconsoleir/token.py
pyapiconsoleir/tests/__init__.py
pyapiconsoleir/tests/helper.py
pyapiconsoleir/tests/mock_api_server.py
pyapiconsoleir/tests/test_postal_code_to_address.py
pyapiconsoleir-0.1.1.dist-info/METADATA
pyapiconsoleir-0.1.1.dist-info/WHEEL
pyapiconsoleir-0.1.1.dist-info/top_level.txt
pyapiconsoleir-0.1.1.dist-info/RECORD
