Metadata-Version: 2.1
Name: pyapiconsoleir
Version: 0.1.1
Summary: UNKNOWN
Home-page: UNKNOWN
Author: mahdi13
License: UNKNOWN
Platform: UNKNOWN
Requires-Dist: requests
Requires-Dist: ujson
Requires-Dist: restfulpy (==0.40.1)
Requires-Dist: nanohttp (==0.26.1)
Requires-Dist: pymlconf (==0.8.6)
Provides-Extra: test
Requires-Dist: nose ; extra == 'test'
Requires-Dist: codecov ; extra == 'test'
